Metadata-Version: 1.0
Name: y-disc-math
Version: 1.0
Summary: Discrethe mathematics functions
Home-page: UNKNOWN
Author: Denis Yamunaque
Author-email: dy.xcvi@gmail.com
License: UNKNOWN
Platform: UNKNOWN
